hang.py
abu_package-1.0.2.dist-info/METADATA
abu_package-1.0.2.dist-info/WHEEL
abu_package-1.0.2.dist-info/top_level.txt
abu_package-1.0.2.dist-info/RECORD
