Metadata-Version: 2.1
Name: abu-package
Version: 1.0.2
Summary: A life changing function.
Author: Junaid Afzal
